shrdlu_blocks/__init__.py
shrdlu_blocks/control.py
shrdlu_blocks/demo.py
shrdlu_blocks/geometry.py
shrdlu_blocks/scenes.py
shrdlu_blocks/typedefs.py
shrdlu_blocks/viewer.py
shrdlu_blocks-0.0.6.dist-info/LICENSE.md
shrdlu_blocks-0.0.6.dist-info/METADATA
shrdlu_blocks-0.0.6.dist-info/WHEEL
shrdlu_blocks-0.0.6.dist-info/top_level.txt
shrdlu_blocks-0.0.6.dist-info/RECORD
