Metadata-Version: 2.1
Name: shrdlu-blocks
Version: 0.0.6
Summary: A simple environment for evaluating and testing natural language understanding systems
Home-page: https://github.com/hosford42/SHRDLUBlocks
Author: Aaron Hosford
Author-email: hosford42@gmail.com
License: MIT
Project-URL: Bug Tracker, https://github.com/hosford42/SHRDLUBlocks/issues
Keywords: NLU,natural language,SHRDLU,blocks
Platform: UNKNOWN
Classifier: Programming Language :: Python :: 3 :: Only
Classifier: Programming Language :: Python :: 3.8
Classifier: License :: OSI Approved :: MIT License
Classifier: Operating System :: OS Independent
Classifier: Intended Audience :: Science/Research
Classifier: Development Status :: 5 - Production/Stable
Classifier: Topic :: Games/Entertainment :: Simulation
Classifier: Topic :: Multimedia :: Graphics
Classifier: Topic :: Scientific/Engineering :: Artificial Intelligence
Classifier: Topic :: Software Development :: Libraries
Classifier: Topic :: Software Development :: Libraries :: Python Modules
Classifier: Topic :: Software Development :: Libraries :: pygame
Classifier: Topic :: Software Development :: User Interfaces
Classifier: Topic :: Text Processing :: Linguistic
License-File: LICENSE.md
Requires-Dist: pygame
